setup.py
tinysvg.egg-info/PKG-INFO
tinysvg.egg-info/SOURCES.txt
tinysvg.egg-info/dependency_links.txt
tinysvg.egg-info/top_level.txt
tinysvg.egg-info/zip-safe
tinysvg/Shapes/Circle.py
tinysvg/Shapes/Element.py
tinysvg/Shapes/Ellipse.py
tinysvg/Shapes/Line.py
tinysvg/Shapes/PolyLine.py
tinysvg/Shapes/Polygon.py
tinysvg/Shapes/Rectangle.py
tinysvg/Shapes/Text.py
tinysvg/Shapes/__init__.py
tinysvg/Turtle/Turtle.py
tinysvg/core/Canvas.py
tinysvg/core/SvgObject.py
tinysvg/core/TinySVG.py
tinysvg/core/__init__.py