Metadata-Version: 1.1
Name: tinysvg
Version: 0.0.3
Summary: tinysvg is a thin implementation of svg within python along with simple turtle graphics. Not production stable.
Home-page: https://github.com/yyttr3/tinysvg
Author: Christian Beasley
Author-email: christianbeasley0@gmail.com
License: MIT
Keywords: svg web turtle graphics
Platform: UNKNOWN
Classifier: Development Status :: 3 - Alpha
Classifier: Intended Audience :: Developers
Classifier: License :: OSI Approved :: MIT License
Classifier: Operating System :: OS Independent
Classifier: Programming Language :: Python :: 3 :: Only
Classifier: Topic :: Multimedia :: Graphics
Classifier: Topic :: Internet
